{
    "no_wrap": true,
    "title": "顶点",
    "text_block_list": [
        {
            "name": "独白",
            "text": "然后，到了URA奖表扬典礼当天──"
        },
        {
            "name": "成田白仁",
            "text": "地图上标的地方就是这里吗……嗯。\n看起来气派十足呢。"
        },
        {
            "name": "独白",
            "text": "本届的表扬典礼似乎办在与往年不同的会场。\n……从入口处起就充满了庄严的气氛。"
        },
        {
            "name": "成田白仁",
            "text": "呵，才刚到这里，看来就已经值回票价了。\n训练员，你看。"
        },
        {
            "name": "成田白仁",
            "text": "我们能亲眼看到……\n那些举世无双的强者们了。"
        },
        {
            "name": "成田白仁",
            "text": "目白麦昆与美浦波旁。",
            "color_text_info_list": [
                "目白麦昆",
                "美浦波旁"
            ]
        },
        {
            "name": "独白",
            "text": "目白麦昆……在决定长距离最强选手的舞台\n“天皇赏（春）”创下连胜纪录，\n是赛马娘界最顶尖的长途跑者。"
        },
        {
            "name": "独白",
            "text": "另一位则是美浦波旁，\n她也曾被选为年度代表赛马娘，\n靠训练锻炼起来的身体及持久力是她的武器。"
        },
        {
            "name": "成田白仁",
            "text": "而另一边是小栗帽与……",
            "color_text_info_list": [
                "小栗帽"
            ]
        },
        {
            "name": "独白",
            "text": "小栗帽是从地方崭露头角后，\n席卷了中央赛事的赛马娘。\n其支持度与实力足以称为赛马娘界的顶尖。"
        },
        {
            "name": "成田白仁",
            "text": "──鲁道夫象征啊。"
        },
        {
            "name": "琵琶晨光",
            "text": "这活动也会邀请得奖者以外的选手，\n以表示慰劳之意呢。"
        },
        {
            "name": "成田白仁",
            "text": "大姐。"
        },
        {
            "name": "琵琶晨光",
            "text": "呵呵。因为看到今天的主角，\n就抢先来打招呼了。"
        },
        {
            "name": "琵琶晨光",
            "text": "听说今年之所以规定穿决胜服，\n似乎也是因你而起的策划哦。\n毕竟专为赛跑打造的服装才是赛马娘的──"
        },
        {
            "name": "成田白仁",
            "text": "……那种听了令人头大的详细说明就免了。"
        },
        {
            "name": "琵琶晨光",
            "text": "什么！？我的头才不大好吗！"
        },
        {
            "name": "成田白仁",
            "text": "我没有在讲大姐你的头。"
        },
        {
            "name": "琵琶晨光",
            "text": "……总之。我们快点进去吧。"
        },
        {
            "name": "琵琶晨光",
            "text": "不管怎么说，\n你应该有想好得奖感言了吧？"
        },
        {
            "name": "成田白仁",
            "text": "…………\n感言？"
        },
        {
            "name": "琵琶晨光",
            "text": "咦！难、难道你……"
        },
        {
            "name": "成田白仁",
            "text": "……训练员。",
            "choice_data_list": [
                "你只要用最诚实的心意回答问题就好"
            ]
        },
        {
            "name": "成田白仁",
            "text": "原来如此。"
        },
        {
            "name": "琵琶晨光",
            "text": "……你真的明白吗？"
        },
        {
            "name": "主持人",
            "text": "──那么，本届年度代表赛马娘──\n成田白仁小姐！\n请上台！"
        },
        {
            "name": "四周",
            "text": "哦哦……！"
        },
        {
            "name": "成田白仁",
            "text": "……"
        },
        {
            "name": "记者A",
            "text": "成田白仁真有大将之风呢～！\n这样下去超越鲁道夫也不无可能吧？"
        },
        {
            "name": "记者B",
            "text": "会想看到她们两个正面对决呢～！\n到底谁才是最强的呢？"
        },
        {
            "name": "主持人",
            "text": "成田白仁小姐，\n恭喜你得奖！"
        },
        {
            "name": "成田白仁",
            "text": "谢谢。"
        },
        {
            "name": "成田白仁",
            "text": "……"
        },
        {
            "name": "主持人",
            "text": "……"
        },
        {
            "name": "主持人",
            "text": "呃、呃……对了！\n那么关于这次得奖的感言，\n你最想献给谁呢？"
        },
        {
            "name": "成田白仁",
            "text": "……这个嘛。"
        },
        {
            "name": "成田白仁",
            "text": "我想献给聚集在此处，实力坚强的赛马娘们。"
        },
        {
            "name": "两人",
            "text": "！"
        },
        {
            "name": "两人",
            "text": "……"
        },
        {
            "name": "成田白仁",
            "text": "我刚跑完经典级。\n接下来才要跑古马级的比赛。"
        },
        {
            "name": "成田白仁",
            "text": "因此虽然我被选为年度代表赛马娘，\n但我还没跟聚集此处的所有赛马娘们较量过。\n这样……我仍能被称之为最强吗？"
        },
        {
            "name": "成田白仁",
            "text": "并不能。这东西只是暂定的。\n就算要我现在立刻退还奖赏跟称号也无妨。"
        },
        {
            "name": "主持人",
            "text": "咦！？"
        },
        {
            "name": "成田白仁",
            "text": "我要再次向聚集在此处的赛马娘问一句──\n“要不要来一场赌上顶点的较量？”"
        },
        {
            "name": "成田白仁",
            "text": "──来比比看，你们跟我到底谁比较强。"
        },
        {
            "name": "独白",
            "text": "（哗然……！）"
        },
        {
            "name": "成田白仁",
            "text": "──我说完了。"
        },
        {
            "name": "主持人",
            "text": "请、请等一下！\n我们还有预定事项要……"
        },
        {
            "name": "成田白仁",
            "text": "但我没有。比赛见。"
        },
        {
            "name": "记者A",
            "text": "……这太夸张了。\n竟然向全体赛马娘宣战……？"
        },
        {
            "name": "记者B",
            "text": "这、这个目标可不是超越鲁道夫这么简单！\n简直前所未闻！"
        },
        {
            "name": "记者A",
            "text": "喂，快连络编辑部！\n明天的头条就是“白仁破天荒的挑衅！”"
        },
        {
            "name": "记者A",
            "text": "“向‘皇帝’等所有赛马娘发问，\n打倒成田白仁的会是谁！”"
        },
        {
            "name": "鲁道夫象征",
            "text": "…………呵。"
        },
        {
            "name": "鲁道夫象征",
            "text": "你讲了一席惊天动地的话呢。\n白仁。"
        },
        {
            "name": "独白",
            "text": "当我终于找到成田白仁时，\n她正独自站在会场外头。"
        },
        {
            "name": "成田白仁",
            "text": "……呼。",
            "choice_data_list": [
                "真是惊人的发言啊",
                "真是惊人的发言呢"
            ]
        },
        {
            "name": "成田白仁",
            "text": "是你叫我诚实回答的吧。"
        },
        {
            "name": "成田白仁",
            "text": "我想跑更多比赛，然后获胜。\n仅此而已。"
        },
        {
            "name": "独白",
            "text": "不知道是否已经预见了今后将要发生的事情，\n成田白仁露出了大胆无畏的微笑。"
        }
    ]
}