{
    "no_wrap": true,
    "title": "Maya的比赛讲座☆",
    "text_block_list": [
        {
            "text": "和摩耶重炮一起看完模拟赛后，\n回去的路上──"
        },
        {
            "name": "春丽",
            "text": "啊，是小MAYA和训练员～！\n你们难道是来帮我加油的吗！？"
        },
        {
            "name": "摩耶重炮",
            "text": "嗯！\n乌拉拉很努力呢～☆"
        },
        {
            "name": "春丽",
            "text": "嘿嘿，谢谢～！"
        },
        {
            "name": "春丽",
            "text": "今天也跑得非常开心哦！\n虽然是最后一名，但我跑得很满足♪"
        },
        {
            "name": "摩耶重炮",
            "text": "是吗～乌拉拉真厉害～！\n人家只要输了就会闹别扭☆"
        },
        {
            "name": "春丽",
            "text": "我一直都很开心哦！\n因为我最喜欢跑步了！"
        },
        {
            "name": "春丽",
            "text": "不过……要赢还真难！\n小MAYA是怎么赢得比赛的？"
        },
        {
            "name": "摩耶重炮",
            "text": "我吗？"
        },
        {
            "name": "春丽",
            "text": "嗯！\n你不是一直都跑得很快吗～？"
        },
        {
            "name": "春丽",
            "text": "乌拉拉要是也能像小MAYA一样的话，\n说不定就能赢了！",
            "choice_data_list": [
                "要不要一起练习？"
            ]
        },
        {
            "name": "摩耶重炮",
            "text": "好主意☆"
        },
        {
            "name": "摩耶重炮",
            "text": "乌拉拉，我们一起练习，\n下次一定要获胜！！"
        },
        {
            "name": "摩耶重炮",
            "text": "人家和训练员的比赛讲座～☆\n学生是乌拉拉同学♪"
        },
        {
            "name": "春丽",
            "text": "有！\n我是乌拉拉！"
        },
        {
            "name": "摩耶重炮",
            "text": "那就立刻开始吧～！\n首先是向训练员发问哦☆"
        },
        {
            "name": "摩耶重炮",
            "text": "乌拉拉现在需要的是什么！？",
            "choice_data_list": [
                "增强体力避免筋疲力尽！",
                "掌握超越对手的诀窍！"
            ]
        },
        {
            "name": "摩耶重炮",
            "text": "叮咚叮咚☆\n训练员果然厉害♪"
        },
        {
            "name": "摩耶重炮",
            "text": "……嗯哼！\n那个，乌拉拉同学！"
        },
        {
            "name": "摩耶重炮",
            "text": "讲白了☆之前比赛的时候，\n你跑到一半就没力了吧！？"
        },
        {
            "name": "春丽",
            "text": "嗯！\n虽然跑得很开心，但快累瘫了～"
        },
        {
            "name": "摩耶重炮",
            "text": "如果有更多体力，\n就能更轻松地跑完了吧～☆"
        },
        {
            "name": "春丽",
            "text": "对耶！\n小MAYA真聪明～♪"
        },
        {
            "name": "摩耶重炮",
            "text": "噗噗！人家今天是老师，\n要叫我“摩耶重炮老师”！"
        },
        {
            "name": "春丽",
            "text": "是的，摩耶重炮老师！"
        },
        {
            "text": "就这样，在摩耶重炮的指导下，\n春丽进行了训练──"
        },
        {
            "name": "摩耶重炮",
            "text": "呀～☆这就是所谓的心有灵犀！？\n人家也在想同样的事情～♪"
        },
        {
            "name": "摩耶重炮",
            "text": "乌拉拉，我问你，\n你平常都是怎么跑的？"
        },
        {
            "name": "春丽",
            "text": "平常？\n我都是拿出全力在跑哦！"
        },
        {
            "name": "摩耶重炮",
            "text": "嗯，这样啊……\n那么，有什么让你伤脑筋的事情吗？"
        },
        {
            "name": "春丽",
            "text": "嗯～我很难取得领先呢～\n感觉要撞到别人的时候我就会变得很慌张！"
        },
        {
            "name": "摩耶重炮",
            "text": "哦哦，原来如此～！"
        },
        {
            "name": "摩耶重炮",
            "text": "那么，\n下场比赛就盯着前面跑吧！"
        },
        {
            "name": "摩耶重炮",
            "text": "只要紧盯着前面，\n就会遇到前面都没人的时候──"
        },
        {
            "name": "摩耶重炮",
            "text": "等到那时候，\n就直直地往前冲☆"
        },
        {
            "name": "春丽",
            "text": "我知道了！\n我会试试看的♪"
        },
        {
            "name": "春丽",
            "text": "听我说，听我说！\n我超过一个人了！"
        },
        {
            "name": "摩耶重炮",
            "text": "哇，太棒了～！\n超过一个人──"
        },
        {
            "name": "摩耶重炮",
            "text": "一个人！？"
        },
        {
            "name": "春丽",
            "text": "嘿嘿～！就这样分别超过每一个人，\n最后要拿下第一名～♪"
        },
        {
            "name": "摩耶重炮",
            "text": "只要不断超越别人，总有一天会是第一名！\n一定要拿下第一名～！！"
        },
        {
            "name": "春丽",
            "text": "哦～！！"
        },
        {
            "text": "给春丽的指导\n似乎对摩耶重炮带来了正面影响。"
        }
    ]
}