{
    "no_wrap": true,
    "title": "名指导",
    "text_block_list": [
        {
            "name": "待兼诗歌剧",
            "text": "呼啊……抵达终点！"
        },
        {
            "name": "双涡轮",
            "text": "唔～～！又被追过了～～！！"
        },
        {
            "name": "双涡轮",
            "text": "诗歌剧，你是不是换过引擎了！"
        },
        {
            "name": "待兼诗歌剧",
            "text": "咦？可是我身上本来就没有引擎啊！？"
        },
        {
            "name": "双涡轮",
            "text": "因为你咻──一下就进步好多！\n一定是动了什么手脚吧！"
        },
        {
            "name": "待兼诗歌剧",
            "text": "唔～可是，我也没特别做什么，\n就跟平常一样啊……"
        },
        {
            "name": "待兼诗歌剧",
            "text": "跟平常一样吃饭、一样睡觉，\n训练也是一如往常──"
        },
        {
            "name": "待兼诗歌剧",
            "text": "再来就是训练员有教我脚要怎么施力，\n还有面对比赛该抱持什么心态之类的而已。"
        },
        {
            "name": "两人",
            "text": "…………"
        },
        {
            "name": "两人",
            "text": "就是这个！！"
        },
        {
            "name": "待兼诗歌剧",
            "text": "原来如此。虽然我做事还是一样平凡，\n但训练员就不是等闲之辈了……！"
        },
        {
            "name": "双涡轮",
            "text": "所以，诗歌剧的训练员\n就等于是诗歌剧的引擎！"
        },
        {
            "name": "待兼诗歌剧",
            "text": "喔喔，训练员就是我的引擎……！"
        },
        {
            "name": "待兼诗歌剧",
            "text": "嘿嘿嘿！\n感觉好像在跑两人三脚一样，不错耶！"
        },
        {
            "name": "独白",
            "text": "那天，待兼诗歌剧\n突然对我表达了好几次感谢！"
        }
    ]
}