{
    "no_wrap": true,
    "title": "迎向札幌纪念",
    "text_block_list": [
        {
            "name": "待兼福来",
            "text": "好，我们来到“札幌纪念”了哦，\n训练员！"
        },
        {
            "name": "待兼福来",
            "text": "咦？在房间角落装饰着一棵树耶。\n那是……",
            "choice_data_list": [
                "是紫丁香树吧",
                "是紫丁香树呢"
            ]
        },
        {
            "name": "待兼福来",
            "text": "哦？原来是叫这个名字啊？\n不过，为什么这里会有这种树……"
        },
        {
            "name": "待兼福来",
            "text": "啊，上面写着说明文字。紫丁香是\n札幌市的代表树木。原来如此……"
        },
        {
            "name": "待兼福来",
            "text": "啊！？训练员，我察觉到一件\n很惊人的事情了！\n这感觉非常吉利呢！"
        },
        {
            "name": "待兼福来",
            "text": "紫丁香英文是Lilac……\n念出来就是“来Luck”！\n这样我绝对可以拿下好成绩的！",
            "choice_data_list": [
                "原来如此……"
            ]
        },
        {
            "name": "待兼福来",
            "text": "看来我只能收下这份祝福了。南无南无～\n北方之神啊，伟大的神威啊～"
        },
        {
            "name": "待兼福来",
            "text": "请赐给我幸运吧～\n还有我想吃成吉思汗烤肉～"
        }
    ]
}