{
    "no_wrap": true,
    "title": "迎向春季S",
    "text_block_list": [
        {
            "name": "美浦波旁",
            "text": "重新确认资讯。草地1800米竞赛。\n直线310米，终点前存在2.2米\n高低差的陡坡。"
        },
        {
            "name": "美浦波旁",
            "text": "确定是对出道前的我过于严苛的条件。\n但对现在的我来说──",
            "choice_data_list": [
                "一定能跑完！"
            ]
        },
        {
            "name": "美浦波旁",
            "text": "是，这样的几率在上升当中。"
        },
        {
            "name": "美浦波旁",
            "text": "为了面对“皋月赏”，\n我一定会全力跑完今天的1800米。"
        },
        {
            "name": "美浦波旁",
            "text": "应该说，要是今天无法达成……\n或许更改路线才是明智的决定。"
        },
        {
            "name": "独白",
            "text": "美浦波旁冷静地提议，\n让我更加感受到她的决心。",
            "choice_data_list": [
                "波旁一定没问题的！",
                "波旁一定没问题的哦！"
            ]
        },
        {
            "name": "美浦波旁",
            "text": "是，Master……！"
        },
        {
            "name": "独白",
            "text": "“皋月赏”的试金石，\n“春季S”就此开幕！"
        }
    ]
}