{
    "no_wrap": true,
    "title": "情人节",
    "text_block_list": [
        {
            "name": "强击",
            "text": "呀～～\n那个巧克力，太可爱了！"
        },
        {
            "name": "强击",
            "text": "也太棒了吧？\n闪闪亮亮超有档次的！\n我想买那个～"
        },
        {
            "name": "强击的朋友A",
            "text": "你还真是喜欢这种看起来很贵的东西啊。\n不如，你就给训练员送这个吧？"
        },
        {
            "name": "强击",
            "text": "嗯，这想法不错。\n然后再多买一份给我自己吃♡"
        },
        {
            "name": "强击的朋友B",
            "text": "怎么还带买自己份的啊喂。\n话说回来，还挺让我意外的——"
        },
        {
            "name": "强击的朋友B",
            "text": "一直念叨着训练员，\n你超喜欢他的吧？"
        },
        {
            "name": "强击",
            "text": "嗯，最喜欢了♡\n所以情人节要送他礼物！"
        },
        {
            "name": "强击的朋友B",
            "text": "说这话也不害臊。\n嘛算了，不过你真觉得只是“买”就好了吗？"
        },
        {
            "name": "强击",
            "text": "诶？"
        },
        {
            "name": "强击的朋友A",
            "text": "确实。会想给稀饭的人*亲手做东西呢！\n我也会给恋人做蛋糕哦～\n（*原文“好きピ”是年轻人之间流行的混种语）"
        },
        {
            "name": "强击的朋友B ",
            "text": "哈！？你这家伙什么时候！？\n给我详细地讲讲！"
        },
        {
            "name": "强击",
            "text": "……那个。\n亲手做的，会让人开心吗？"
        },
        {
            "name": "强击",
            "text": "你看我不是很喜欢高档的东西吗？"
        },
        {
            "name": "强击",
            "text": "所以，我会觉得\n上档次的东西更让人开心。"
        },
        {
            "name": "强击的朋友A",
            "text": "诶…………这个嘛，\n从喜欢的人那里得到手工品也会很开心吧？"
        },
        {
            "name": "强击的朋友B",
            "text": "不过训练员怎么想的，\n我们也不知道就是了……"
        },
        {
            "name": "强击的朋友B",
            "text": "毕竟我们是学生，\n也可能会觉得分量太重而不接受。"
        },
        {
            "name": "强击的朋友A",
            "text": "诶，也就是说如果收下了的话……\n那不是超有戏的！？"
        },
        {
            "name": "强击",
            "text": "……！"
        },
        {
            "name": "强击",
            "text": "有戏……"
        },
        {
            "name": "强击",
            "text": "……诶，我难道，\n希望和训练员亲，有戏吗！？"
        },
        {
            "name": "强击的朋友A",
            "text": "诶！？\n突然怎么了！？"
        },
        {
            "name": "强击",
            "text": "总觉得那个……\n我对训练员亲，是这种感觉吗！"
        },
        {
            "name": "强击的朋友B",
            "text": "虽然不知道是哪种感觉……难道不是吗？"
        },
        {
            "name": "强击",
            "text": "………………不知道。"
        },
        {
            "name": "强击",
            "text": "诶、诶、诶、诶！？\n搞不明白啦～！"
        },
        {
            "name": "强击",
            "text": "训练员亲，就和姐姐们一样……\n对我又温柔，又宠爱……"
        },
        {
            "name": "强击",
            "text": "……所以，最喜——"
        },
        {
            "name": "强击",
            "text": "………………"
        },
        {
            "name": "强击",
            "text": "好困扰啊……"
        },
        {
            "name": "独白",
            "text": "某天强击的训练结束后，\n我正在训练员室工作时——"
        },
        {
            "name": "强击",
            "text": "训练员。",
            "choice_data_list": [
                "强击？"
            ]
        },
        {
            "name": "独白",
            "text": "不知道为什么强击进来的时候很老实。\n这种气氛，总觉得有点怀念……\n对了，是签约前的时候……"
        },
        {
            "name": "独白",
            "text": "以为自己被误解了的强击，\n拿出勇气，认真地向我说出了\n自己对梦想的想法。"
        },
        {
            "name": "强击",
            "text": "……",
            "choice_data_list": [
                "……没事的，有话就说吧"
            ]
        },
        {
            "name": "强击",
            "text": "诶？",
            "choice_data_list": [
                "什么都可以，我都会接受的",
                "什么都可以，我都会接受的"
            ]
        },
        {
            "name": "强击",
            "text": "……！！！！"
        },
        {
            "name": "强击",
            "text": "也、也没到那种程度啦！"
        },
        {
            "name": "强击",
            "text": "这个！\n就是想把这个给你而已！"
        },
        {
            "name": "强击",
            "text": "情人节快乐，\n训练员亲！",
            "choice_data_list": [
                "……情人节！"
            ]
        },
        {
            "name": "强击",
            "text": "嗯，是啊。\n在地下商场买的！"
        },
        {
            "name": "强击",
            "text": "这种巧克力，\n在迪拜也很有人气～\n当时正好赶上限时售卖♡",
            "choice_data_list": [
                "谢谢！"
            ]
        },
        {
            "name": "强击",
            "text": "嗯！"
        },
        {
            "name": "强击",
            "text": "白色情人节的回礼，\n我很期待哦♡"
        },
        {
            "name": "强击",
            "text": "啊～紧张死了。"
        },
        {
            "name": "强击",
            "text": "就因为她们说了奇怪的话。\n明明训练员亲就是训练员亲啊！"
        },
        {
            "name": "强击",
            "text": "……他收下了啊。"
        },
        {
            "name": "强击",
            "text": "……早知道这样，或许亲手做会更好吧。"
        },
        {
            "name": "强击",
            "text": "……真的吗？"
        },
        {
            "name": "强击",
            "text": "真的都会接受吗？"
        },
        {
            "name": "独白",
            "text": "看到强击下定决心认真的样子。\n作为训练员的我……\n自然也有自信接受她的全部心意。",
            "choice_data_list": [
                "当然会了"
            ]
        },
        {
            "name": "强击",
            "text": "那——"
        },
        {
            "name": "强击",
            "text": "这个，你能收下吗？",
            "choice_data_list": [
                "这是……？"
            ]
        },
        {
            "name": "强击",
            "text": "这是我做的，\n手工巧克力！"
        },
        {
            "name": "强击",
            "text": "情人节快乐，\n训练员。",
            "choice_data_list": [
                "情人节…………"
            ]
        },
        {
            "name": "独白",
            "text": "我被这句话吓了一跳。\n今天是情人节。然后她刚才说的话……",
            "choice_data_list": [
                "强击，你这是——"
            ]
        },
        {
            "name": "强击",
            "text": "！！"
        },
        {
            "name": "强击",
            "text": "啊，等、等一下！\n稍微……等一下。"
        },
        {
            "name": "强击",
            "text": "…………那个。\n希望你能收下。"
        },
        {
            "name": "强击",
            "text": "我也，搞不明白了。\n虽然搞不明白……"
        },
        {
            "name": "强击",
            "text": "我对训练员的感觉，\n就和对姐姐她们一样……"
        },
        {
            "name": "强击",
            "text": "最喜欢了，\n这点绝对可以保证。"
        },
        {
            "name": "强击",
            "text": "所以，收下也没关系吧？\n不会让你困扰的吧……？",
            "choice_data_list": [
                "……谢谢！"
            ]
        },
        {
            "name": "强击",
            "text": "！"
        },
        {
            "name": "强击",
            "text": "……欸嘿嘿。\n嗯。"
        },
        {
            "name": "强击",
            "text": "训练员亲……\n一直以来谢谢你了。"
        }
    ]
}