{
    "no_wrap": true,
    "title": "夏季集训（第二年）途中",
    "text_block_list": [
        {
            "name": "独白",
            "text": "（涮涮──……涮涮──……）"
        },
        {
            "name": "曼城茶座",
            "text": "咦……关于“朋友”的事……是吗？",
            "choice_data_list": [
                "嗯，我想要详细了解",
                "嗯，我想要详细了解"
            ]
        },
        {
            "name": "独白",
            "text": "某个晚上，我向曼城茶座\n询问了关于在她心中\n占据最重分量的存在。"
        },
        {
            "name": "独白",
            "text": "我之前曾在偶然的情况下听她说过。\n记得，那时候是──"
        },
        {
            "name": "曼城茶座",
            "text": "……和我很像的……“朋友”……\n一直引导着我……非常、重要的……"
        },
        {
            "name": "曼城茶座",
            "text": "……从小时候开始，就丝毫没有改变……\n一直跑在我前方的赛马娘……我的……憧憬……"
        },
        {
            "name": "独白",
            "text": "她和“朋友”似乎是在小时候相遇的。\n但她口中的“引导”，\n具体来说究竟是指什么事呢？"
        },
        {
            "name": "曼城茶座",
            "text": "你想要……知道什么呢？",
            "choice_data_list": [
                "你说她会引导你，是什么意思呢？"
            ]
        },
        {
            "name": "曼城茶座",
            "text": "引导就是……她总是……\n“跑在我前面”的意思。"
        },
        {
            "name": "曼城茶座",
            "text": "不对，这么说不太对，\n并非只有这样而已……"
        },
        {
            "name": "曼城茶座",
            "text": "“朋友”会将我……\n带去幸福的地方……"
        },
        {
            "name": "？？？",
            "text": "呵呵呵、呵呵呵呵呵……♪"
        },
        {
            "name": "曼城茶座",
            "text": "像是偷偷带我去一些没有人知道，\n安静的场所……"
        },
        {
            "name": "？？？",
            "text": "呵呵呵、呵呵呵呵呵……♪"
        },
        {
            "name": "曼城茶座",
            "text": "去游乐园的时候……她坐在摩天轮的最上面。\n当时我为了追上她而坐进摩天轮的车厢……\n就看见了一片很美的景色……"
        },
        {
            "name": "曼城茶座",
            "text": "只要追着“朋友”，\n总是会发生快乐的事……"
        },
        {
            "name": "曼城茶座",
            "text": "若我希望，她也总是会告诉我\n该往哪里去……"
        },
        {
            "name": "曼城茶座",
            "text": "其他人……从来……没给过我什么……\n但只有“朋友”不一样。"
        },
        {
            "name": "曼城茶座",
            "text": "她是唯一……会带给我快乐时光……\n独一无二的存在……",
            "choice_data_list": [
                "现在……也只有她一个吗？"
            ]
        },
        {
            "name": "曼城茶座",
            "text": "现在的话……抱歉，我更正。\n训练员感觉也跟“朋友”有点相似。"
        },
        {
            "name": "曼城茶座",
            "text": "但我之所以能遇见训练员，\n也是因为“朋友”把我引导到\n特雷森学园的关系。"
        },
        {
            "name": "独白",
            "text": "──我有点明白了。\n“朋友”不仅仅是比赛时跑在前方的存在……"
        },
        {
            "name": "独白",
            "text": "对曼城茶座来说，\n或许更像是“幸福的领航员”。"
        },
        {
            "name": "曼城茶座",
            "text": "现在也是，只要我希望，\n她就会带我到任何地方。譬如说……"
        },
        {
            "name": "曼城茶座",
            "text": "训练员，你可以帮我想一个\n“这种地方绝对不可能有的东西”吗？"
        },
        {
            "name": "独白",
            "text": "这里不可能有的东西……\n难道“朋友”会引导我们\n去那样东西的所在处吗？"
        },
        {
            "name": "独白",
            "text": "我当下立刻想到的是──",
            "choice_data_list": [
                "薰衣草",
                "球藻"
            ]
        },
        {
            "name": "曼城茶座",
            "text": "薰衣草……是吗。\n唇形科薰衣草属……\n是不会生长在这里的花……"
        },
        {
            "name": "曼城茶座",
            "text": "但是，只要我由衷地希望……"
        },
        {
            "name": "独白",
            "text": "（　碰　！　）"
        },
        {
            "name": "独白",
            "text": "我的背……突然被某种强大的力量推了一下。\n当我浑身冷汗，同时像是被人催促似地\n朝被推的方向前进时──"
        },
        {
            "name": "曼城茶座",
            "text": "这是……岩石呢。\n一起把它给移开吧。"
        },
        {
            "name": "曼城茶座",
            "text": "一～二……嗯嗯……"
        },
        {
            "name": "独白",
            "text": "她以那纤细的手臂使劲将岩石移开，\n而岩石底下──"
        },
        {
            "name": "曼城茶座",
            "text": "有很多的……海草呢。\n每一根海草的前端都有像花苞的东西……"
        },
        {
            "name": "曼城茶座",
            "text": "……是用这个，\n来代替薰衣草的意思吗……"
        },
        {
            "name": "独白",
            "text": "或许这就是“朋友”能做到的极限了吧。\n看来她并非万能。"
        },
        {
            "name": "独白",
            "text": "也许是类似于会尽力帮忙的\n“守护灵”吧。"
        },
        {
            "name": "曼城茶座",
            "text": "球藻……是吗。\n生长在北海道阿寒湖等处的，球状藻类……"
        },
        {
            "name": "曼城茶座",
            "text": "虽然这附近应该不可能找得到，\n但是，只要我由衷地希望……"
        },
        {
            "name": "独白",
            "text": "（　碰　！　）"
        },
        {
            "name": "独白",
            "text": "我的背……突然被某种强大的力量推了一下。\n当我浑身冷汗，同时像是被人催促似地\n朝被推的方向前进时──"
        },
        {
            "name": "曼城茶座",
            "text": "哈啊、哈啊，我们……走了很远呢。"
        },
        {
            "name": "曼城茶座",
            "text": "啊，训练员……\n那个被浪打到沙滩上的东西是……"
        },
        {
            "name": "独白",
            "text": "那个东西──是藻类的块状物。"
        },
        {
            "name": "独白",
            "text": "吸收了大量海里的污水后，\n打结成一块的植物残骸……"
        },
        {
            "name": "曼城茶座",
            "text": "虽然外观不讨喜……\n但这是用来……代替球藻的意思吗？"
        },
        {
            "name": "独白",
            "text": "或许这就是“朋友”能做到的极限了吧。\n看来她并非万能。"
        },
        {
            "name": "独白",
            "text": "也许是类似于会尽力帮忙的\n“守护灵”吧。"
        },
        {
            "name": "曼城茶座",
            "text": "她总是会像这样，\n引导我笔直地走向幸福。"
        },
        {
            "name": "曼城茶座",
            "text": "一直在我身边，帮助着我……\n非常重要的……“朋友”……"
        },
        {
            "name": "独白",
            "text": "曼城茶座能有今天，\n或许都是这位守护灵的功劳\n也不一定。"
        },
        {
            "name": "曼城茶座",
            "text": "……啊，训练员你看。\n海上有一座小岛……"
        },
        {
            "name": "曼城茶座",
            "text": "我有点想要去看看呢……\n想必…会是个安静又美丽的地方吧。"
        },
        {
            "name": "独白",
            "text": "我望向远处的海上……的确有一座小岛。\n但既没有通往岛上的桥和船，\n也不是游泳能到达的距离。"
        },
        {
            "name": "独白",
            "text": "要是认真想要\n去到那座岛上的话──"
        },
        {
            "name": "独白",
            "text": "（碰、碰、碰──！！）"
        },
        {
            "name": "独白",
            "text": "没来由地，我的背上被连续戳了几下……！\n像是在告诉我“不要犹豫，去吧”。"
        },
        {
            "name": "曼城茶座",
            "text": "啊，“朋友”她……\n在跟我招手……"
        },
        {
            "name": "曼城茶座",
            "text": "她在海的另一边招手说“来这里”……",
            "choice_data_list": [
                "──！？"
            ]
        },
        {
            "name": "独白",
            "text": "像是“守护灵”般的存在，\n但──"
        },
        {
            "name": "独白",
            "text": "──却让人搞不清楚\n究竟有没有心要守护她。"
        }
    ]
}