{
    "no_wrap": true,
    "title": "举办Grand Masters！",
    "text_block_list": [
        {
            "name": "独白",
            "text": "“SWBC”结束后，迎来了新的一年。\n训练员们感受到至今与赛马娘一起走过的\n足迹有多么珍贵。"
        },
        {
            "name": "独白",
            "text": "希望自己与赛马娘的足迹，也能像\n三女神传授的知识背后\n那些赛马娘和训练员一样流传后世。"
        },
        {
            "name": "独白",
            "text": "之后──"
        },
        {
            "name": "独白",
            "text": "参加过“SWBC”，\n且表现特别接近顶点的赛马娘们，\n受邀参加“Grand Masters”。"
        },
        {
            "name": "独白",
            "text": "三女神掌管许多赛马娘的资料，\n跑法也立于赛马娘的顶点──\n接下来终于要与她们对决了……！"
        }
    ]
}