{
    "no_wrap": true,
    "text_block_list": [
        {
            "name": "特别周",
            "text": "“大和抚子，在此登场！\n坚定不移的摔跤手，草～上飞～！”"
        },
        {
            "name": "神鹰",
            "text": "呃！？小特！？\n……你是不是吃了什么不好的东西？"
        },
        {
            "name": "草上飞",
            "text": "呵呵呵……\n“让你们见识见识，北海道之子的志气！\n超强意志力摔跤手，特～别、周～！”"
        },
        {
            "name": "神鹰",
            "text": "…………！！\n呵……呵呵呵、啊～哈哈哈！"
        },
        {
            "name": "神鹰",
            "text": "在此登场！现在上阵！\n世界最强、疾风怒涛、电光石火的\n蒙面摔跤手！"
        },
        {
            "name": "神鹰",
            "text": "其名为！"
        },
        {
            "name": "两人",
            "text": "祝你生日快乐，神鹰！"
        },
        {
            "name": "神鹰",
            "text": "……！！唔～～～！！\n谢谢你们～～～～！！"
        },
        {
            "name": "特别周",
            "text": "生日快乐，小神！\n食堂的派对已经准备好啰！"
        },
        {
            "name": "草上飞",
            "text": "小青和圣王她们，\n也已经先过去等我们啰～"
        },
        {
            "name": "神鹰",
            "text": "我去我去，现在就去～！"
        },
        {
            "name": "神鹰",
            "text": "……今天、就只有今天、稍微一下下而已。\n就算是戴着面罩的神鹰，也可以哭一下。"
        }
    ]
}