{
    "no_wrap": true,
    "title": "＜First＞队的公开宣战",
    "text_block_list": [
        {
            "name": "独白",
            "text": "在为终于要开始的“青春杯”\n正式赛准备中的某天，\n小小蚕茧来到了训练员室。"
        },
        {
            "name": "小小蚕茧",
            "text": "……不是什么重要的事。"
        },
        {
            "name": "小小蚕茧",
            "text": "只是假如你和这支队伍\n进入“青春杯”决赛……"
        },
        {
            "name": "小小蚕茧",
            "text": "要是竞赛表现太糟糕的话绝不原谅你们。\n若不认真对决就没有意义。"
        },
        {
            "name": "小小蚕茧",
            "text": "只有这件事，就这样──"
        },
        {
            "name": "苦涩糖衣",
            "text": "咦，真巧呀！\n你也来公开宣战了啊！"
        },
        {
            "name": "小小蚕茧",
            "text": "啊！？才、才没……没那回事！"
        },
        {
            "text": "接受了来自小小蚕茧和\n苦涩糖衣的公开宣战──"
        },
        {
            "text": "<chrname>她，\n稍微变得更有干劲了。"
        },
        {
            "text": "队伍变得更有干劲了！"
        },
        {
            "text": "尤其是队伍对于“速度”的\n热烈情感，\n给<chrname>带来了影响！"
        },
        {
            "text": "队伍变得更有干劲了！"
        },
        {
            "text": "尤其是队伍对于“持久力”的\n热烈情感，\n给<chrname>带来了影响！"
        },
        {
            "text": "队伍变得更有干劲了！"
        },
        {
            "text": "尤其是队伍对于“力量”的\n热烈情感，\n给<chrname>带来了影响！"
        },
        {
            "text": "队伍变得更有干劲了！"
        },
        {
            "text": "尤其是队伍对于“意志力”的\n热烈情感，\n给<chrname>带来了影响！"
        },
        {
            "text": "队伍变得更有干劲了！"
        },
        {
            "text": "尤其是队伍对于“智力”的\n热烈情感，\n给<chrname>带来了影响！"
        },
        {
            "text": "队伍变得更有干劲了！"
        },
        {
            "text": "尤其是队伍对于“速度”的\n极为热烈情感，\n给<chrname>带来了影响！"
        },
        {
            "text": "队伍变得更有干劲了！"
        },
        {
            "text": "尤其是队伍对于“持久力”的\n极为热烈情感，\n给<chrname>带来了影响！"
        },
        {
            "text": "队伍变得更有干劲了！"
        },
        {
            "text": "尤其是队伍对于“力量”的\n极为热烈情感，\n给<chrname>带来了影响！"
        },
        {
            "text": "队伍变得更有干劲了！"
        },
        {
            "text": "尤其是队伍对于“意志力”的\n极为热烈情感，\n给<chrname>带来了影响！"
        },
        {
            "text": "队伍变得更有干劲了！"
        },
        {
            "text": "尤其是队伍对于“智力”的\n极为热烈情感，\n给<chrname>带来了影响！"
        }
    ]
}