{
    "no_wrap": true,
    "title": "爆进！　夏季庙会！",
    "text_block_list": [
        {
            "text": "在海边的集训场所里进行的夏季集训，来到了最后一天。"
        },
        {
            "name": "樱花进王",
            "text": "哦哦ー，今天也是好天气！\n真棒！　真让人有干劲呢！"
        },
        {
            "name": "樱花进王",
            "text": "那么，马上开始训练吧！"
        },
        {
            "name": "樱花进王",
            "text": "作为模范的我，时间的利用方案也是完美的！！\n1秒钟也不会浪费！"
        },
        {
            "name": "马娘A",
            "text": "――所以说，真的很期待今天晚上呢～♪\n好久没参加过庙会了。苹果糖什么的会有卖吗？"
        },
        {
            "name": "马娘B",
            "text": "应该会有吧？　但我可是杏子糖派的哦。\n那个一口的大小很可爱呢ー"
        },
        {
            "name": "樱花进王",
            "text": "……嗯嗯，庙会？\n今天，竟然还有这种东西吗？",
            "choice_data_list": [
                "训练完之后去看看吧"
            ]
        },
        {
            "name": "樱花进王",
            "text": "我现在也正想这么说呢！\n哼哼，我和训练员好像心意相通了呢！"
        },
        {
            "name": "樱花进王",
            "text": "那么今天的训练结束后就去庙会吧！\n训练也会更加投入的！"
        },
        {
            "text": "沙滩上的训练结束后，\n按照约定，到了去参加庙会的时间――"
        },
        {
            "text": "（嘈杂声……）"
        },
        {
            "name": "马娘A",
            "text": "等等……这些都是要庙会的人吗？　……太多了吧？"
        },
        {
            "name": "马娘B",
            "text": "是呢……这样的话，庙会那儿也会很拥挤吧。\n一定注意不要走散了。"
        },
        {
            "text": "果然，庙会现场会非常拥挤。\n我很担心会不会和樱花进王走散了……"
        },
        {
            "name": "樱花进王",
            "text": "让您久等了，训练员！　我已经准备好了！\n来，让我们去参加庙会吧！！",
            "choice_data_list": [
                "有件事你要答应我"
            ]
        },
        {
            "name": "樱花进王",
            "text": "好，是什么呢？",
            "choice_data_list": [
                "注意不要在庙会里走散了",
                "注意不要在庙会里场走散了"
            ]
        },
        {
            "name": "樱花进王",
            "text": "嗯嗯，那当然！\n作为班长，这是理所应当会注意的！",
            "choice_data_list": [
                "如果走散了一定要联系我",
                "如果走散了一定要联系我"
            ]
        },
        {
            "name": "樱花进王",
            "text": "哦哦，这就是所谓的『报告、联络、商谈』吧！！\n可以的，就交给本班长吧！！",
            "choice_data_list": [
                "……你有带手机吗？",
                "………你有带手机吗？"
            ]
        },
        {
            "name": "樱花进王",
            "text": "嗯，当然！！\n好好放在包里了！"
        },
        {
            "name": "樱花进王",
            "text": "……啊啊啊啊！？　是啊，包里！\n忘ーーーー得一干二净了！"
        },
        {
            "name": "樱花进王",
            "text": "但是请放心！　我马上回房间里拿！"
        },
        {
            "text": "对于会不会走散这件事，我已经开始不安了……"
        },
        {
            "name": "樱花进王",
            "text": "哦哦哦ーー！！　好多的摊位！　美食！　盂兰盆会舞！"
        },
        {
            "name": "樱花进王",
            "text": "我想起了小时候和父母一起来的事……\n射击和捞金鱼，父母都夸我很拿手。"
        },
        {
            "name": "樱花进王",
            "text": "我，变得非常ーー非常开心了！！"
        },
        {
            "name": "樱花进王",
            "text": "机会难得，把所有的摊位都逛一遍吧！\n那么，准备――",
            "choice_data_list": [
                "等等……！！",
                "等等……！！"
            ]
        },
        {
            "name": "樱花进王",
            "text": "――爆进ーーーーーー！！！！",
            "choice_data_list": [
                "不要在这种地方爆进啊ー！！"
            ]
        },
        {
            "text": "我立刻伸出手去，但已经来不及了，\n樱花进王全力前进，消失于人群当中……"
        },
        {
            "text": "庙会里人头攒动，我找不到樱花进王的身影。"
        },
        {
            "text": "即使打电话过去，也是『暂时无法接通』。\n别无选择，只能去寻人广播了――"
        },
        {
            "name": "樱花进王",
            "text": "训练员ーーーーーーーーーーー！！！！"
        },
        {
            "name": "樱花进王",
            "text": "你听见了吗，训练员ーー！！\n我在这里，樱花进王在这里哦ー！！"
        },
        {
            "text": "人群中，传来了樱花进王的声音――"
        },
        {
            "name": "樱花进王",
            "text": "喂喂听得见吗！？\n训练员……屏幕全黑了！？"
        },
        {
            "name": "樱花进王",
            "text": "训练员ーーーーー！！！　你在哪里ーーーーー！！\n我手机的屏幕变黑了ーー！！！"
        },
        {
            "text": "樱花进王的手机屏幕一片漆黑。\n而且，我的手机也一次都没响过……也就是说。",
            "choice_data_list": [
                "把你的手机开机啊！！",
                "把你的手机开机啊！！"
            ]
        },
        {
            "name": "樱花进王",
            "text": "等下！？　这么一说，电源好像……\n呀呀呀呀！？　这不是训练员吗！"
        },
        {
            "name": "樱花进王",
            "text": "你来接我，真是感谢感激！！\n我以为我再也见不到你了！",
            "choice_data_list": [
                "至少，你还试着要联系我……",
                "至少，你还试着要联系我……"
            ]
        },
        {
            "name": "樱花进王",
            "text": "那当然了！！"
        },
        {
            "name": "樱花进王",
            "text": "我是樱花进王，值得信赖的班长！\n约定是绝对会遵守的！"
        },
        {
            "name": "樱花进王",
            "text": "而且，我坚信训练员说的话，\n永远都是正确而善良的！！"
        },
        {
            "name": "樱花进王",
            "text": "是的，和我一样ーーー！！",
            "choice_data_list": [
                "能再会真是太好了"
            ]
        },
        {
            "name": "樱花进王",
            "text": "正是如此！"
        },
        {
            "name": "樱花进王",
            "text": "人这么多，我还担心训练员会不会\n被卷入什么事件中了呢！"
        },
        {
            "name": "樱花进王",
            "text": "但是！　我们彼此都平安无事！"
        },
        {
            "name": "樱花进王",
            "text": "训练员找到了我，\n我也找到了训练员！"
        },
        {
            "name": "樱花进王",
            "text": "真是双赢的关系！！\n今后也一起努力吧！　爆进！！"
        },
        {
            "text": "到底哪里双赢了――我没有问她，\n在回荡着庙会音乐的星空下，我与樱花进王热情地握手了。"
        }
    ]
}