{
    "no_wrap": true,
    "title": "Let's Goー开运之旅",
    "text_block_list": [
        {
            "name": "独白",
            "text": "某个休息日，我正在学园里散步的时候……"
        },
        {
            "name": "待兼福来",
            "text": "姆姆姆！？　等一下，那边那位！\n你的面相很奇怪哦！"
        },
        {
            "name": "待兼福来",
            "text": "简单来说，你今天下午肯定是要跟我一起出门吧！\r\n感恩啊～，感恩啊～！",
            "choice_data_list": [
                "我想起来还重要的事，所以……"
            ]
        },
        {
            "name": "待兼福来",
            "text": "啊啊啊！？　请等一下，训练员！\n听我说！　请先听我说啊～！"
        },
        {
            "name": "待兼福来",
            "text": "今天不用上课也不用训练……\n所以，我想上街自由地玩一玩。"
        },
        {
            "name": "待兼福来",
            "text": "但是早晨醒来后的牛奶占卜吓了我一跳！\n今天的运势竟然是“大凶”！"
        },
        {
            "name": "待兼福来",
            "text": "但是我又不想浪费难得的休息日，\r\n于是就得出了一个结论。"
        },
        {
            "name": "待兼福来",
            "text": "对，就是要收集能提升运势的东西来防身。\r\n现在我所有的口袋里都塞满了开运道具！",
            "choice_data_list": [
                "我也算其中之一……？",
                "我也算其中之一……？"
            ]
        },
        {
            "name": "待兼福来",
            "text": "有『承蒙关照的人能招来幸运』的说法～！\r\n所以说无论如何！　无论如何都跟我一起去吧～！！"
        },
        {
            "name": "独白",
            "text": "待兼福来哭着恳求道。\r\n最终我们两个人还是一起出门了。"
        },
        {
            "name": "待兼福来",
            "text": "首先去粗点心店哦！\n在这儿占卜一下训练员的运势吧。"
        },
        {
            "name": "待兼福来",
            "text": "请买一个能抽奖的粗点心试试吧。\n这样就能知道运势了！"
        },
        {
            "name": "独白",
            "text": "我试着买了条口香糖――"
        },
        {
            "name": "待兼福来",
            "text": "哦哦，这不是中了吗！？\r\n中了奖的人，当然就是“大吉”了！"
        },
        {
            "name": "待兼福来",
            "text": "那么接下来轮到我了……现在已经有了幸运道具防身，\r\n说不定能颠覆早晨牛奶占卜的结果呢！"
        },
        {
            "name": "独白",
            "text": "待兼福来鼓足干劲，也打开了\r\n口香糖的包装纸――"
        },
        {
            "name": "待兼福来",
            "text": "什么也没标……也就是说这是“中吉”！",
            "choice_data_list": [
                "没中还是“中吉”，太宽松了吧？"
            ]
        },
        {
            "name": "待兼福来",
            "text": "没什么的。现在就流行这么宽松嘛。\n来，去下一个地方吧，下一个！"
        },
        {
            "name": "待兼福来",
            "text": "这里是杂货店！\n我们在这儿寻找开运道具吧。"
        },
        {
            "name": "待兼福来",
            "text": "哦哦哦，这么快就发现稀有的东西了！　这个达摩*，\r\n一开始就画上了两只眼睛啊！！\r\n（*一种不倒翁，眼睛部分一般是先保留空白）"
        },
        {
            "name": "待兼福来",
            "text": "一般是愿望实现了才会给画上，\r\n但它现在就已经完成任务了……！"
        },
        {
            "name": "待兼福来",
            "text": "劳驾，请给我3个这个。\n我要拿来收藏用、神坛用和传教用。"
        },
        {
            "name": "独白",
            "text": "我们自在享受着这样的散步。\r\n然后――"
        },
        {
            "name": "待兼福来",
            "text": "果然该来神社作为收尾吧。拍拍手祈愿！\n感谢今天这一天平安无事ー。"
        },
        {
            "name": "待兼福来",
            "text": "哎呀，占卜和挑选良辰吉日行事，真的都很好啊。\n它们总是在背后为我助力。从那时起，一直。",
            "choice_data_list": [
                "那时？"
            ]
        },
        {
            "name": "待兼福来",
            "text": "是的！　我自打很小的时候就开始相信占卜了。\r\n我那时就是个喜欢跑步的孩子……"
        },
        {
            "name": "待兼福来",
            "text": "但因为我跑得很慢，所以每回都没有参加运动会的勇气。\r\n但是有一天我做梦……"
        },
        {
            "name": "Shiraoki大人",
            "text": "福来，福来啊。去跑吧。\r\n那样的话，你会取得第一名的吧。"
        },
        {
            "name": "小时候的待兼福来",
            "text": "诶诶诶，真的？　你是……"
        },
        {
            "name": "待兼福来",
            "text": "那就是我与Shiraoki大人的相遇……然后我像她说的那样\n去跑了，真的获得了第一名！"
        },
        {
            "name": "待兼福来",
            "text": "从那以后，我比赛之前就一定会占卜，\r\n或者用开运道具祈愿。"
        },
        {
            "name": "待兼福来",
            "text": "开运道具对我来说就是幸运的轨迹！　就是胜利的蹄铁！"
        },
        {
            "name": "待兼福来",
            "text": "没有那些道具的话，我就只是个困在闸门里的马娘……\n一点儿也动弹不得。"
        },
        {
            "name": "待兼福来",
            "text": "所以说不能扔掉它们。\r\n那样的话自己好像就会回到一无所有的时候……"
        },
        {
            "name": "独白",
            "text": "对待兼福来而言，占卜和开运道具，\r\n无疑是推动了她前进的重要存在。"
        },
        {
            "name": "独白",
            "text": "但是如果过度依赖的话，她就会变成个没了这些东西就什么\r\n都办不到的孩子。 　我感觉到了其危险性――",
            "choice_data_list": [
                "我们要不要试试？"
            ]
        },
        {
            "name": "待兼福来",
            "text": "诶？　试试，是试什么？"
        },
        {
            "name": "待兼福来",
            "text": "唔……玩抓娃娃机就可以了是吧。"
        },
        {
            "name": "待兼福来",
            "text": "交给我吧！　让你来见识一下，\r\n塞进口袋里的开运道具的力量吧！",
            "choice_data_list": [
                "把所有开运道具都拿出来"
            ]
        },
        {
            "name": "待兼福来",
            "text": "诶诶！？　你在说什么呢！\r\n没有了开运道具，在抓娃娃机里是不可能夹到奖品的！"
        },
        {
            "name": "待兼福来",
            "text": "而且今天我的运势是“大凶”……别说夹到\r\n奖品了，都有可能投进去钱还没法操作！",
            "choice_data_list": [
                "那只要把店员给叫来就行了"
            ]
        },
        {
            "name": "待兼福来",
            "text": "不行啊～！　办不到啊～！"
        },
        {
            "name": "独白",
            "text": "我说服了叫嚷着的待兼福来，\r\n把她带的所有开运道具都给没收了。"
        },
        {
            "name": "待兼福来",
            "text": "呜呜呜……这下我就成了纯度100％的大凶马娘了……",
            "choice_data_list": [
                "来，试试看吧"
            ]
        },
        {
            "name": "待兼福来",
            "text": "不可能夹到的……因为现在的我没有任何力量。\nNo More保佑，No More期待……"
        },
        {
            "name": "待兼福来",
            "text": "这样的话，至少请能带来幸运的训练员\r\n陪在我身边吧～。"
        },
        {
            "name": "独白",
            "text": "我与这样恳求着的待兼福来保持着距离，\r\n让她一个人玩抓娃娃机。结果是――"
        },
        {
            "name": "待兼福来",
            "text": "好了，没夹到。那倒也是……\n因为我没有了开运道具赐予的力量。",
            "choice_data_list": [
                "好，再来一次！"
            ]
        },
        {
            "name": "待兼福来",
            "text": "诶……？　我可以再玩一次吗？\n那、那就恭敬不如从命……"
        },
        {
            "name": "独白",
            "text": "之后，经过多次的游戏，终于――"
        },
        {
            "name": "独白",
            "text": "（啪嗒！）"
        },
        {
            "name": "待兼福来",
            "text": "奇怪？　夹到，了……？"
        },
        {
            "name": "待兼福来",
            "text": "我夹到了哦，训练员！",
            "choice_data_list": [
                "就算没有开运道具也能夹到是吧？",
                "就算没有开运道具也能夹到是吧？"
            ]
        },
        {
            "name": "待兼福来",
            "text": "确实……也就是说，即使没有了开运道具的力量，\r\n幸运也是会来的……？"
        },
        {
            "name": "待兼福来",
            "text": "哈啊～……不知怎么，我心情变得轻松了。\n当知道了自己不用带着堆积如山的开运道具了之后。",
            "choice_data_list": [
                "过分依赖道具也不好哦",
                "过分依赖道具也不好哦"
            ]
        },
        {
            "name": "待兼福来",
            "text": "是，我知道了！　说的是呢。我实在是过于畏惧了。\r\n今后我会缩减数量的。"
        },
        {
            "name": "待兼福来",
            "text": "哎呀～，今天成了值得纪念的黄道吉日。\n是我人生中的一大转机。"
        },
        {
            "name": "待兼福来",
            "text": "而且今天得到的赠品玩偶，可谓是吉祥物！\n是新的开运道具！"
        },
        {
            "name": "待兼福来",
            "text": "……不过，不能再增加开运道具了来着。\n诶嘿嘿……那，我就送给附近的乖孩子们吧。"
        },
        {
            "name": "待兼福来",
            "text": "我有现在的这些，以及训练员就足够了！\r\n稍微断舍离也能事随人愿的！"
        },
        {
            "name": "独白",
            "text": "待兼福来笑着向我点头。\n我好像有把她的观念往好的方向去转变了。"
        }
    ]
}