{
    "no_wrap": true,
    "title": "温泉旅行",
    "text_block_list": [
        {
            "text": "某一天，\n我跟往常一样和米浴一起进行训练──"
        },
        {
            "name": "美浦波旁",
            "text": "米浴，辛苦了。"
        },
        {
            "name": "米浴",
            "text": "辛、辛苦了！"
        },
        {
            "name": "米浴",
            "text": "……呵呵。"
        },
        {
            "name": "美浦波旁",
            "text": "为什么要笑？"
        },
        {
            "name": "米浴",
            "text": "啊、没有！那个……"
        },
        {
            "name": "米浴",
            "text": "米浴只是觉得，波旁的伤能治好真是太好了。\n……往后我们还能一起继续奔跑呢。"
        },
        {
            "name": "美浦波旁",
            "text": "……是啊。"
        },
        {
            "name": "美浦波旁",
            "text": "现在已经顺利痊愈。\n应该是有把重点放在消除疲劳，\n尝试包含汤疗在内各种治疗方式的成果。"
        },
        {
            "name": "米浴",
            "text": "汤疗……？"
        },
        {
            "name": "美浦波旁",
            "text": "就是泡温泉。"
        },
        {
            "name": "米浴",
            "text": "原来如此！是泡温泉！"
        },
        {
            "name": "米浴",
            "text": "──温泉？"
        },
        {
            "name": "商店街人员",
            "text": "天啊！恭喜────！！\n抽到特等奖“温泉旅游券”了～～～～！！"
        },
        {
            "name": "米浴",
            "text": "……温泉！！"
        },
        {
            "name": "米浴",
            "text": "哥、哥哥！！"
        },
        {
            "name": "米浴",
            "text": "大、姐姐！！"
        },
        {
            "text": "我和泪眼汪汪的米浴匆忙确认了\n“温泉旅游券”的使用期限，\n赶紧前往旅馆──"
        },
        {
            "text": "泡温泉中……"
        },
        {
            "name": "米浴",
            "text": "呼……好棒的温泉呢……\n米浴觉得好舒服……"
        },
        {
            "name": "米浴",
            "text": "嘿嘿，快看快看。\n脚都暖呼呼的，感觉比平常还要柔软～",
            "choice_data_list": [
                "这是温泉的效果呢",
                "这是温泉的效果呢"
            ]
        },
        {
            "name": "米浴",
            "text": "嗯。现在不管是怎么样的伸展操，\n米浴感觉都能轻松做到！"
        },
        {
            "text": "米浴一脸开心地看着自己的脚。"
        },
        {
            "text": "──她用着那双脚，\n至今在比赛中赢得了无数的胜利。"
        },
        {
            "text": "希望这次的温泉\n能够稍微消除她过去的疲劳……"
        },
        {
            "name": "米浴",
            "text": "嗯？怎么了，哥哥？",
            "choice_data_list": [
                "希望你能一直这么有精神"
            ]
        },
        {
            "name": "米浴",
            "text": "嗯？怎么了，姐姐？",
            "choice_data_list": [
                "希望你能一直这么有精神"
            ]
        },
        {
            "name": "米浴",
            "text": "嘿嘿……谢谢你，哥哥。"
        },
        {
            "name": "米浴",
            "text": "嘿嘿……谢谢你，姐姐。"
        },
        {
            "name": "米浴",
            "text": "放心吧，米浴可以靠这双脚，\n永远奔驰下去的。"
        },
        {
            "name": "米浴",
            "text": "毕竟已经一路努力奔驰过来了嘛。\n不管是“天皇赏（春）”\n还是“宝冢纪念”──"
        },
        {
            "name": "米浴",
            "text": "……都跟哥哥一起。",
            "choice_data_list": [
                "说得也是",
                "说得也是"
            ]
        },
        {
            "name": "米浴",
            "text": "……都跟姐姐一起。",
            "choice_data_list": [
                "说得也是",
                "说得也是"
            ]
        },
        {
            "name": "米浴",
            "text": "嗯！"
        },
        {
            "name": "米浴",
            "text": "呵呵，哥哥。\n下次要参加什么竞赛呢？",
            "choice_data_list": [
                "米浴想参加什么？"
            ]
        },
        {
            "name": "米浴",
            "text": "呵呵，姐姐。\n下次要参加什么竞赛呢？",
            "choice_data_list": [
                "米浴想参加什么？"
            ]
        },
        {
            "name": "米浴",
            "text": "嘿嘿嘿，米浴嘛──"
        },
        {
            "text": "我就这样和米浴一起谈论着关于未来的规划。"
        },
        {
            "text": "我在这段时光中，\n深刻地感受到了\n与米浴之间无可取代的情谊……"
        }
    ]
}