{
    "no_wrap": true,
    "title": "自我介绍",
    "text_block_list": [
        {
            "name": "独白",
            "text": "现在起，我和签约赛马娘\n一起在闪耀系列赛奔驰的日子就要开始了。\n要和我并肩前进的她叫做──",
            "color_text_info_list": [
                "闪耀系列赛"
            ]
        },
        {
            "name": "奇锐骏",
            "text": "你好，训练员。\n我就是奇锐骏。",
            "color_text_info_list": [
                "奇锐骏"
            ]
        },
        {
            "name": "奇锐骏",
            "text": "请你尽管锻炼我。\n别看我这样，我的身体可是很健壮的呢。"
        },
        {
            "name": "奇锐骏",
            "text": "那我们就不慌不忙地，\n朝着目标慢慢前进吧。"
        },
        {
            "name": "独白",
            "text": "就这样，\n我与<chrname>\n要开始挑战闪耀系列赛了！"
        }
    ]
}