{
    "no_wrap": true,
    "text_block_list": [
        {
            "name": "莱茵力量",
            "text": "……训练员，我有事想和你商量。\n我想你大概也知道了——"
        },
        {
            "name": "莱茵力量",
            "text": "汇集了三后冠比赛录像的\n『后冠之轨迹』系列出版了最新作！"
        },
        {
            "name": "莱茵力量",
            "text": "就是，那个~……虽然挺贵的……\n但是但是，对于训练员来说，\n这应该是很有用的资料！　所以说——"
        },
        {
            "name": "莱茵力量",
            "text": "要、要是你打算买的话……\n之后可以借我一下吗？\n我的零花钱根本都不够的~……！"
        },
        {
            "name": "莱茵力量",
            "text": "……拜、拜托了——！"
        }
    ]
}