{
    "no_wrap": true,
    "text_block_list": [
        {
            "name": "アストンマーチャン",
            "text": "ででっでっででーん♪\nこちらエージェント・マー。\nターゲットを確認したのです。"
        },
        {
            "name": "アストンマーチャン",
            "text": "昨日見た映画をまねっこマーちゃんです。\n気分はマーちゃんカーをかっ飛ばし、\n任務を遂行するエージェントなのです。"
        },
        {
            "name": "アストンマーチャン",
            "text": "ずきゅーん、どーん。\n『マーちゃん、アストンマーチャンだ』\n……ふっ。"
        },
        {
            "name": "アストンマーチャン",
            "text": "ふふ、マスコットが天職でなければ、\nマーちゃんはエージェントマーちゃんを\n目指していたかもしれません。"
        }
    ]
}